sc_cli/__init__.py
sc_cli/main.py
solar_circuit-0.1.3.dist-info/licenses/LICENSE
solar_circuit-0.1.3.dist-info/METADATA
solar_circuit-0.1.3.dist-info/WHEEL
solar_circuit-0.1.3.dist-info/top_level.txt
solar_circuit-0.1.3.dist-info/RECORD
