Metadata-Version: 2.4
Name: solar-circuit
Version: 0.1.3
Summary: CLI-based AI development framework
Author-email: Your Name <your.email@example.com>
License-Expression: MIT
Requires-Python: >=3.10
License-File: LICENSE
Requires-Dist: typer[all]
Requires-Dist: rich
Requires-Dist: gitpython
Requires-Dist: python-frontmatter
Requires-Dist: google-generativeai
Requires-Dist: keyring
Requires-Dist: toml
Requires-Dist: watchdog
Provides-Extra: dev
Requires-Dist: pytest; extra == "dev"
Requires-Dist: pytest-cov; extra == "dev"
Requires-Dist: flake8; extra == "dev"
Dynamic: license-file
